ThreeDVG/__init__.py
ThreeDVG/app.py
ThreeDVG/models.py
ThreeDVG/ThreeDVG/__init__.py
ThreeDVG/ThreeDVG/data/__init__.py
ThreeDVG/ThreeDVG/data/scannet/__init__.py
ThreeDVG/ThreeDVG/data/scannet/batch_load_scannet_data.py
ThreeDVG/ThreeDVG/data/scannet/load_scannet_data.py
ThreeDVG/ThreeDVG/data/scannet/model_util_scannet.py
ThreeDVG/ThreeDVG/data/scannet/scannet_utils.py
ThreeDVG/ThreeDVG/data/scannet/visualize.py
ThreeDVG/ThreeDVG/data/scannet/meta_data/__init__.py
ThreeDVG/ThreeDVG/data/scannet/meta_data/nyu40_labels.csv
ThreeDVG/ThreeDVG/data/scannet/meta_data/scannet_means.npz
ThreeDVG/ThreeDVG/data/scannet/meta_data/scannet_reference_means.npz
ThreeDVG/ThreeDVG/data/scannet/meta_data/scannetv2-labels.combined.tsv
ThreeDVG/ThreeDVG/data/scannet/meta_data/scannetv2.txt
ThreeDVG/ThreeDVG/data/scannet/meta_data/scannetv2_test.txt
ThreeDVG/ThreeDVG/data/scannet/meta_data/scannetv2_train.txt
ThreeDVG/ThreeDVG/data/scannet/meta_data/scannetv2_val.txt
ThreeDVG/ThreeDVG/lib/__init__.py
ThreeDVG/ThreeDVG/lib/ap_helper.py
ThreeDVG/ThreeDVG/lib/config.py
ThreeDVG/ThreeDVG/lib/dataset.py
ThreeDVG/ThreeDVG/lib/enet.py
ThreeDVG/ThreeDVG/lib/eval_helper.py
ThreeDVG/ThreeDVG/lib/loss.py
ThreeDVG/ThreeDVG/lib/loss_helper.py
ThreeDVG/ThreeDVG/lib/projection.py
ThreeDVG/ThreeDVG/lib/solver.py
ThreeDVG/ThreeDVG/lib/pointnet2/__init__.py
ThreeDVG/ThreeDVG/lib/pointnet2/_version.py
ThreeDVG/ThreeDVG/lib/pointnet2/pointnet2_modules.py
ThreeDVG/ThreeDVG/lib/pointnet2/pointnet2_test.py
ThreeDVG/ThreeDVG/lib/pointnet2/pointnet2_utils.py
ThreeDVG/ThreeDVG/lib/pointnet2/pytorch_utils.py
ThreeDVG/ThreeDVG/lib/pointnet2/setup.py
ThreeDVG/ThreeDVG/models/__init__.py
ThreeDVG/ThreeDVG/models/backbone_module.py
ThreeDVG/ThreeDVG/models/containers.py
ThreeDVG/ThreeDVG/models/lang_module.py
ThreeDVG/ThreeDVG/models/match_module.py
ThreeDVG/ThreeDVG/models/proposal_module.py
ThreeDVG/ThreeDVG/models/refnet.py
ThreeDVG/ThreeDVG/models/voting_module.py
ThreeDVG/ThreeDVG/models/detr/__init__.py
ThreeDVG-0.1.10.dist-info/METADATA
ThreeDVG-0.1.10.dist-info/WHEEL
ThreeDVG-0.1.10.dist-info/top_level.txt
ThreeDVG-0.1.10.dist-info/RECORD
