Metadata-Version: 2.1
Name: ThreeDVG
Version: 0.1.10
Summary: Visual Ground
Home-page: https://github.com/yjzhao19981027/ThreeDVG
Download-URL: https://github.com/yjzhao19981027/ThreeDVG/tags
Author: Yinjie Zhao
Author-email: 630877986@qq.com
Requires-Python: >=3.7
Requires-Dist: pillow
Requires-Dist: easydict
Requires-Dist: fastapi
Requires-Dist: h5py
Requires-Dist: plyfile
Requires-Dist: trimesh
